{
  "build": "py312h6a678d5_0",
  "build_number": 0,
  "channel": "https://repo.anaconda.com/pkgs/main/linux-64",
  "constrains": [],
  "depends": [
    "libgcc-ng >=11.2.0",
    "libstdcxx-ng >=11.2.0",
    "python >=3.12,<3.13.0a0"
  ],
  "extracted_package_dir": "/home/hambal/robot-learning-practice/anaconda3/pkgs/kiwisolver-1.4.4-py312h6a678d5_0",
  "files": [
    "lib/python3.12/site-packages/kiwisolver-1.4.4.dist-info/INSTALLER",
    "lib/python3.12/site-packages/kiwisolver-1.4.4.dist-info/LICENSE",
    "lib/python3.12/site-packages/kiwisolver-1.4.4.dist-info/METADATA",
    "lib/python3.12/site-packages/kiwisolver-1.4.4.dist-info/RECORD",
    "lib/python3.12/site-packages/kiwisolver-1.4.4.dist-info/REQUESTED",
    "lib/python3.12/site-packages/kiwisolver-1.4.4.dist-info/WHEEL",
    "lib/python3.12/site-packages/kiwisolver-1.4.4.dist-info/direct_url.json",
    "lib/python3.12/site-packages/kiwisolver-1.4.4.dist-info/top_level.txt",
    "lib/python3.12/site-packages/kiwisolver/__init__.py",
    "lib/python3.12/site-packages/kiwisolver/__pycache__/__init__.cpython-312.pyc",
    "lib/python3.12/site-packages/kiwisolver/_cext.cpython-312-x86_64-linux-gnu.so",
    "lib/python3.12/site-packages/kiwisolver/_cext.pyi",
    "lib/python3.12/site-packages/kiwisolver/py.typed"
  ],
  "fn": "kiwisolver-1.4.4-py312h6a678d5_0.conda",
  "license": "BSD-3-Clause",
  "link": {
    "source": "/home/hambal/robot-learning-practice/anaconda3/pkgs/kiwisolver-1.4.4-py312h6a678d5_0",
    "type": 1
  },
  "md5": "47e12eaa774b108e6e17011b1d727650",
  "name": "kiwisolver",
  "package_tarball_full_path": "/home/hambal/robot-learning-practice/anaconda3/pkgs/kiwisolver-1.4.4-py312h6a678d5_0.conda",
  "paths_data": {
    "paths": [],
    "paths_version": 1
  },
  "requested_spec": "defaults/linux-64::kiwisolver==1.4.4=py312h6a678d5_0[md5=47e12eaa774b108e6e17011b1d727650]",
  "sha256": "0a5e7983c66b5f25e2395c209a9241287c095f050023ba038bca12439e427b99",
  "size": 69665,
  "subdir": "linux-64",
  "timestamp": 1698847531000,
  "url": "https://repo.anaconda.com/pkgs/main/linux-64/kiwisolver-1.4.4-py312h6a678d5_0.conda",
  "version": "1.4.4"
}